{
  "data": [
    {
      "sensor_id": 1,
      "name": "N/A",
      "temperature": 20,
      "humidity": 25,
      "id": "8851"
    },
    {
      "sensor_id": 2,
      "name": "N/A",
      "id": "3435"
    },
    {
      "sensor_id": 3,
      "name": "N/A",
      "temperature": 13,
      "id": "1875"
    },
    {
      "sensor_id": 4,
      "name": "N/A",
      "humidity": 58,
      "id": "12c1"
    },
    {
      "sensor_id": 5,
      "name": "N/A",
      "temperature": 23,
      "humidity": 59,
      "id": "ccc5"
    },
    {
      "sensor_id": 6,
      "name": "N/A",
      "id": "37ee"
    },
    {
      "sensor_id": 7,
      "name": "N/A",
      "temperature": 19,
      "id": "0b61"
    },
    {
      "sensor_id": 8,
      "name": "N/A",
      "humidity": 35,
      "id": "8a13"
    },
    {
      "sensor_id": 9,
      "name": "N/A",
      "temperature": 22,
      "humidity": 50,
      "id": "9cb3"
    },
    {
      "sensor_id": 10,
      "name": "N/A",
      "id": "a6f1"
    },
    {
      "sensor_id": 11,
      "name": "N/A",
      "temperature": 20,
      "id": "b94b"
    },
    {
      "sensor_id": 12,
      "name": "N/A",
      "humidity": 57,
      "id": "90ee"
    },
    {
      "sensor_id": 13,
      "name": "N/A",
      "temperature": 22,
      "humidity": 55,
      "id": "a651"
    },
    {
      "sensor_id": 14,
      "name": "N/A",
      "id": "1ce3"
    },
    {
      "sensor_id": 15,
      "name": "N/A",
      "temperature": 13,
      "id": "c8fc"
    },
    {
      "sensor_id": 16,
      "name": "N/A",
      "humidity": 45,
      "id": "cb1b"
    },
    {
      "sensor_id": 17,
      "name": "N/A",
      "temperature": 21,
      "humidity": 35,
      "id": "9164"
    },
    {
      "sensor_id": 18,
      "name": "N/A",
      "id": "9230"
    },
    {
      "sensor_id": 19,
      "name": "N/A",
      "temperature": 20,
      "id": "c8e7"
    },
    {
      "sensor_id": 20,
      "name": "N/A",
      "humidity": 35,
      "id": "eb27"
    }
  ]
}